[
  {
    "id": "fire",
    "title": "Thru the Fire",
    "subtitle": "Survival \u00b7 rebuilding \u00b7 purpose",
    "description": "A project about surviving loss, rebuilding with intention, and deciding what matters most.",
    "cover": "https://static.wixstatic.com/media/85e419_c239fc27c20a40f2abd513484fe2164f~mv2.png",
    "audio": "https://static.wixstatic.com/mp3/85e419_7810e2c471ce46b5a1c5a664b8307995.mp3",
    "video": "https://video.wixstatic.com/video/85e419_f9fc9d5cab4144398fc4e45393a74802/1080p/mp4/file.mp4",
    "poster": "https://static.wixstatic.com/media/85e419_f9fc9d5cab4144398fc4e45393a74802f001.jpg",
    "accent": "#E45B28",
    "accent2": "#230A06",
    "soft": "#F2D0C4",
    "word": "RESILIENCE",
    "featured": true,
    "experience": "games/thru-the-fire/index.html"
  },
  {
    "id": "streams",
    "title": "Streams",
    "subtitle": "Value \u00b7 attention \u00b7 legacy",
    "description": "A project about the difference between attention, value, ownership, and what remains after the current passes.",
    "cover": "https://static.wixstatic.com/media/85e419_f1790cd4078f4745b6bcd2483b0fa5e9~mv2.png",
    "audio": "https://static.wixstatic.com/mp3/85e419_7be9c7aa18ad4a6db00fd1af6ee7dbcd.mp3",
    "video": "https://video.wixstatic.com/video/85e419_02c25299256e42718f0da9a761bff3f2/1080p/mp4/file.mp4",
    "poster": "https://static.wixstatic.com/media/85e419_02c25299256e42718f0da9a761bff3f2f001.jpg",
    "accent": "#168D94",
    "accent2": "#071E22",
    "soft": "#D7F0EF",
    "word": "LEGACY",
    "featured": true,
    "experience": "games/streams/index.html"
  },
  {
    "id": "africa",
    "title": "I Woke Up in Africa",
    "subtitle": "Awakening \u00b7 identity \u00b7 purpose",
    "description": "A project centered on awakening, heritage, service, reflection, and purpose.",
    "cover": "https://static.wixstatic.com/media/85e419_d386a1b9fadc48d788bbb0d8da976d7e~mv2.png",
    "audio": "https://static.wixstatic.com/mp3/85e419_f92713dc5c48443ca1c191bbbb0aec04.mp3",
    "video": "https://video.wixstatic.com/video/85e419_8497a06ad5f84c299342e692290a2679/1080p/mp4/file.mp4",
    "poster": "https://static.wixstatic.com/media/85e419_8497a06ad5f84c299342e692290a2679f001.jpg",
    "accent": "#D18C36",
    "accent2": "#2B1709",
    "soft": "#F3DCC0",
    "word": "AWAKENING",
    "featured": true,
    "experience": "games/africa/index.html"
  },
  {
    "id": "away",
    "title": "I Was Away",
    "subtitle": "Reflection \u00b7 distance \u00b7 return",
    "description": "A reflective project about distance, return, maturity, and perspective.",
    "cover": "https://static.wixstatic.com/media/85e419_0837ebc9c84047b4bb967f5fa5da0a53~mv2.png",
    "audio": "https://static.wixstatic.com/mp3/85e419_506638b15e0a4b49a92b519766eb69ce.mp3",
    "video": "https://video.wixstatic.com/video/85e419_de8f9ec40b844a068eae0ab148b44fb6/1080p/mp4/file.mp4",
    "poster": "https://static.wixstatic.com/media/85e419_de8f9ec40b844a068eae0ab148b44fb6f001.jpg",
    "accent": "#4B748B",
    "accent2": "#0E1B22",
    "soft": "#DDE8ED",
    "word": "REFLECTION",
    "featured": true,
    "experience": ""
  },
  {
    "id": "gettin",
    "title": "Gettin' It",
    "subtitle": "Ambition \u00b7 rhythm \u00b7 momentum",
    "description": "A project about independent momentum, confidence, rhythm, and progress.",
    "cover": "https://static.wixstatic.com/media/85e419_40b87708678f48cfad6446f13195877a~mv2.png",
    "audio": "https://static.wixstatic.com/mp3/85e419_2fdfc2045ce64265a7c62451fa296f6f.mp3",
    "video": "",
    "poster": "",
    "accent": "#D97924",
    "accent2": "#251109",
    "soft": "#F4D9C2",
    "word": "MOMENTUM",
    "featured": false,
    "experience": ""
  },
  {
    "id": "artificial-love",
    "title": "Artificial Love",
    "subtitle": "Connection \u00b7 technology \u00b7 vulnerability",
    "description": "A dark R&B project about emotional distance, desire, technology, and modern connection.",
    "cover": "https://static.wixstatic.com/media/85e419_36678d97dc74448d941a8c306df3acc2~mv2.png",
    "audio": "",
    "video": "",
    "poster": "",
    "accent": "#B7273B",
    "accent2": "#19070B",
    "soft": "#EED6DB",
    "word": "CONNECTION",
    "featured": false,
    "experience": ""
  }
]